{
  "Name": "info_spawngroup_load_unload",
  "Pages": [
    {
      "Game": "cs2",
      "EntityType": "Point",
      "Name": "info_spawngroup_load_unload",
      "Description": "Logical entity that starts async loading or unloading a level.",
      "IconPath": "static/fgd_dump/img/cs2/info_spawngroup_load_unload.png",
      "PageAnnotation": null,
      "Properties": [
        {
          "FriendlyName": "Entity Scripts",
          "InternalName": "vscripts",
          "VariableType": "ScriptList",
          "Description": "Name(s) of script files that are executed after all entities have spawned.",
          "Options": [],
          "Annotations": []
        },
        {
          "FriendlyName": "Name",
          "InternalName": "targetname",
          "VariableType": "TargetSource",
          "Description": "The name that other entities refer to this entity by.",
          "Options": [],
          "Annotations": []
        },
        {
          "FriendlyName": "Name",
          "InternalName": "targetname",
          "VariableType": "TargetSource",
          "Description": "",
          "Options": [],
          "Annotations": []
        },
        {
          "FriendlyName": "Level to stream in/out",
          "InternalName": "mapname",
          "VariableType": "String",
          "Description": "",
          "Options": [],
          "Annotations": []
        },
        {
          "FriendlyName": "Name of entity filter to apply",
          "InternalName": "entityfiltername",
          "VariableType": "String",
          "Description": "",
          "Options": [],
          "Annotations": []
        },
        {
          "FriendlyName": "The landmark (same landmark name should be in both maps) used to determine the offset of the second map to the first",
          "InternalName": "landmark",
          "VariableType": "String",
          "Description": "",
          "Options": [],
          "Annotations": []
        },
        {
          "FriendlyName": "Timeout Interval",
          "InternalName": "timeoutInterval",
          "VariableType": "Float",
          "Description": "The amount of seconds after which, if any client hasn\u0027t finished streaming the necessary assets, that client is disconnected and the spawngroup spawns anyways. 0 means use some reasonable default set in the code.",
          "Options": [],
          "Annotations": []
        },
        {
          "FriendlyName": "Automatically activate and show streamed level",
          "InternalName": "autoactivate",
          "VariableType": "Bool",
          "Description": "Automatically activates the spawn group once loaded.",
          "Options": [],
          "Annotations": []
        }
      ],
      "InputOutputs": [
        {
          "Name": "RunScriptFile",
          "Description": "Load and execute a script file",
          "VariableType": "String",
          "Type": "Input"
        },
        {
          "Name": "RunScriptCode",
          "Description": "Execute a fragment of script code",
          "VariableType": "String",
          "Type": "Input"
        },
        {
          "Name": "CallScriptFunction",
          "Description": "Call a script function",
          "VariableType": "String",
          "Type": "Input"
        },
        {
          "Name": "CallPrivateScriptFunction",
          "Description": "Calls a script function from this entity\u0027s private script scope.",
          "VariableType": "String",
          "Type": "Input"
        },
        {
          "Name": "CallGlobalScriptFunction",
          "Description": "Calls a script function in the global script scope.",
          "VariableType": "String",
          "Type": "Input"
        },
        {
          "Name": "Kill",
          "Description": "Removes this entity from the world.",
          "VariableType": "Void",
          "Type": "Input"
        },
        {
          "Name": "KillHierarchy",
          "Description": "Removes this entity and all its children from the world.",
          "VariableType": "Void",
          "Type": "Input"
        },
        {
          "Name": "KillConstrained",
          "Description": "Removes this entity, all its children, and anything constrained to it, from the world.",
          "VariableType": "Void",
          "Type": "Input"
        },
        {
          "Name": "AddOutput",
          "Description": "Adds an entity I/O connection to this entity. Parameter format: outputname\u0026gt;targetname\u003Einputname\u0026gt;parameter\u0026gt;delay\u0026gt;max times to fire (-1 == infinite). Very dangerous, use with care.",
          "VariableType": "String",
          "Type": "Input"
        },
        {
          "Name": "FireUser1",
          "Description": "Causes this entity\u0027s OnUser1 output to be fired.",
          "VariableType": "Void",
          "Type": "Input"
        },
        {
          "Name": "FireUser2",
          "Description": "Causes this entity\u0027s OnUser2 output to be fired.",
          "VariableType": "Void",
          "Type": "Input"
        },
        {
          "Name": "FireUser3",
          "Description": "Causes this entity\u0027s OnUser3 output to be fired.",
          "VariableType": "Void",
          "Type": "Input"
        },
        {
          "Name": "FireUser4",
          "Description": "Causes this entity\u0027s OnUser4 output to be fired.",
          "VariableType": "Void",
          "Type": "Input"
        },
        {
          "Name": "OnUser1",
          "Description": "Fired in response to FireUser1 input.",
          "VariableType": "Void",
          "Type": "Output"
        },
        {
          "Name": "OnUser2",
          "Description": "Fired in response to FireUser2 input.",
          "VariableType": "Void",
          "Type": "Output"
        },
        {
          "Name": "OnUser3",
          "Description": "Fired in response to FireUser3 input.",
          "VariableType": "Void",
          "Type": "Output"
        },
        {
          "Name": "OnUser4",
          "Description": "Fired in response to FireUser4 input.",
          "VariableType": "Void",
          "Type": "Output"
        },
        {
          "Name": "OnKilled",
          "Description": "Fired when the entity is killed and removed from the game. Parameter is the inflictor.",
          "VariableType": "Void",
          "Type": "Output"
        },
        {
          "Name": "OnSpawnGroupLoadStarted",
          "Description": "Fired when the level starts streaming in.",
          "VariableType": "Void",
          "Type": "Output"
        },
        {
          "Name": "OnSpawnGroupLoadFinished",
          "Description": "Fired when the level finishes streaming in.",
          "VariableType": "Void",
          "Type": "Output"
        },
        {
          "Name": "OnSpawnGroupUnloadStarted",
          "Description": "Fired when the level starts streaming out.",
          "VariableType": "Void",
          "Type": "Output"
        },
        {
          "Name": "OnSpawnGroupUnloadFinished",
          "Description": "Fired when the level finishes streaming out.",
          "VariableType": "Void",
          "Type": "Output"
        },
        {
          "Name": "StartSpawnGroupLoad",
          "Description": "Start loading the level.",
          "VariableType": "Void",
          "Type": "Input"
        },
        {
          "Name": "ActivateSpawnGroup",
          "Description": "Activate the loaded spawn group.",
          "VariableType": "Void",
          "Type": "Input"
        },
        {
          "Name": "StartSpawnGroupUnload",
          "Description": "Start unloading the level.",
          "VariableType": "Void",
          "Type": "Input"
        }
      ]
    },
    {
      "Game": "steamvr",
      "EntityType": "Point",
      "Name": "info_spawngroup_load_unload",
      "Description": "Logical entity that starts async loading or unloading a level.",
      "IconPath": "static/fgd_dump/img/steamvr/info_spawngroup_load_unload.png",
      "PageAnnotation": null,
      "Properties": [
        {
          "FriendlyName": "Entity Scripts",
          "InternalName": "vscripts",
          "VariableType": "ScriptList",
          "Description": "Name(s) of script files that are executed after all entities have spawned.",
          "Options": [],
          "Annotations": []
        },
        {
          "FriendlyName": "Name",
          "InternalName": "targetname",
          "VariableType": "TargetSource",
          "Description": "The name that other entities refer to this entity by.",
          "Options": [],
          "Annotations": []
        },
        {
          "FriendlyName": "Name",
          "InternalName": "targetname",
          "VariableType": "TargetSource",
          "Description": "",
          "Options": [],
          "Annotations": []
        },
        {
          "FriendlyName": "Level to stream in/out",
          "InternalName": "mapname",
          "VariableType": "String",
          "Description": "",
          "Options": [],
          "Annotations": []
        },
        {
          "FriendlyName": "Name of entity filter to apply",
          "InternalName": "entityfiltername",
          "VariableType": "String",
          "Description": "",
          "Options": [],
          "Annotations": []
        },
        {
          "FriendlyName": "The landmark (same landmark name should be in both maps) used to determine the offset of the second map to the first",
          "InternalName": "landmark",
          "VariableType": "String",
          "Description": "",
          "Options": [],
          "Annotations": []
        },
        {
          "FriendlyName": "Timeout Interval",
          "InternalName": "timeoutInterval",
          "VariableType": "Float",
          "Description": "The amount of seconds after which, if any client hasn\u0027t finished streaming the necessary assets, that client is disconnected and the spawngroup spawns anyways. 0 means use some reasonable default set in the code.",
          "Options": [],
          "Annotations": []
        }
      ],
      "InputOutputs": [
        {
          "Name": "RunScriptFile",
          "Description": "Load and execute a script file",
          "VariableType": "String",
          "Type": "Input"
        },
        {
          "Name": "RunScriptCode",
          "Description": "Execute a fragment of script code",
          "VariableType": "String",
          "Type": "Input"
        },
        {
          "Name": "CallScriptFunction",
          "Description": "Call a script function",
          "VariableType": "String",
          "Type": "Input"
        },
        {
          "Name": "CallPrivateScriptFunction",
          "Description": "Calls a script function from this entity\u0027s private script scope.",
          "VariableType": "String",
          "Type": "Input"
        },
        {
          "Name": "CallGlobalScriptFunction",
          "Description": "Calls a script function in the global script scope.",
          "VariableType": "String",
          "Type": "Input"
        },
        {
          "Name": "Kill",
          "Description": "Removes this entity from the world.",
          "VariableType": "Void",
          "Type": "Input"
        },
        {
          "Name": "KillHierarchy",
          "Description": "Removes this entity and all its children from the world.",
          "VariableType": "Void",
          "Type": "Input"
        },
        {
          "Name": "AddOutput",
          "Description": "Adds an entity I/O connection to this entity. Parameter format: outputname\u0026gt;targetname\u003Einputname\u0026gt;parameter\u0026gt;delay\u0026gt;max times to fire (-1 == infinite). Very dangerous, use with care.",
          "VariableType": "String",
          "Type": "Input"
        },
        {
          "Name": "FireUser1",
          "Description": "Causes this entity\u0027s OnUser1 output to be fired.",
          "VariableType": "Void",
          "Type": "Input"
        },
        {
          "Name": "FireUser2",
          "Description": "Causes this entity\u0027s OnUser2 output to be fired.",
          "VariableType": "Void",
          "Type": "Input"
        },
        {
          "Name": "FireUser3",
          "Description": "Causes this entity\u0027s OnUser3 output to be fired.",
          "VariableType": "Void",
          "Type": "Input"
        },
        {
          "Name": "FireUser4",
          "Description": "Causes this entity\u0027s OnUser4 output to be fired.",
          "VariableType": "Void",
          "Type": "Input"
        },
        {
          "Name": "OnUser1",
          "Description": "Fired in response to FireUser1 input.",
          "VariableType": "Void",
          "Type": "Output"
        },
        {
          "Name": "OnUser2",
          "Description": "Fired in response to FireUser2 input.",
          "VariableType": "Void",
          "Type": "Output"
        },
        {
          "Name": "OnUser3",
          "Description": "Fired in response to FireUser3 input.",
          "VariableType": "Void",
          "Type": "Output"
        },
        {
          "Name": "OnUser4",
          "Description": "Fired in response to FireUser4 input.",
          "VariableType": "Void",
          "Type": "Output"
        },
        {
          "Name": "OnKilled",
          "Description": "Fired when the entity is killed and removed from the game.",
          "VariableType": "Void",
          "Type": "Output"
        },
        {
          "Name": "OnSpawnGroupLoadStarted",
          "Description": "Fired when the level starts streaming in.",
          "VariableType": "Void",
          "Type": "Output"
        },
        {
          "Name": "OnSpawnGroupLoadFinished",
          "Description": "Fired when the level finishes streaming in.",
          "VariableType": "Void",
          "Type": "Output"
        },
        {
          "Name": "OnSpawnGroupUnloadStarted",
          "Description": "Fired when the level starts streaming out.",
          "VariableType": "Void",
          "Type": "Output"
        },
        {
          "Name": "OnSpawnGroupUnloadFinished",
          "Description": "Fired when the level finishes streaming out.",
          "VariableType": "Void",
          "Type": "Output"
        },
        {
          "Name": "StartSpawnGroupLoad",
          "Description": "Start loading the level.",
          "VariableType": "Void",
          "Type": "Input"
        },
        {
          "Name": "ActivateSpawnGroup",
          "Description": "Activate the loaded spawn group.",
          "VariableType": "Void",
          "Type": "Input"
        },
        {
          "Name": "StartSpawnGroupUnload",
          "Description": "Start unloading the level.",
          "VariableType": "Void",
          "Type": "Input"
        }
      ]
    }
  ]
}